{
  "1": {
    "Q": "sentence1.png",
    "A": "0",
    "D": "desc1.png",
    "Q_I": "",
    "D_I": "tapestry.jpg"
  },
  "2": {
    "Q": "sentence2.png",
    "A": "0",
    "D": "desc2.png",
    "Q_I": "",
    "D_I": ""
  },
  "3": {
    "Q": "sentence3.png",
    "A": "1",
    "D": "desc3.png",
    "Q_I": "",
    "D_I": "kiritanpo.jpg"
  },
  "4": {
    "Q": "sentence4.png",
    "A": "0",
    "D": "desc4.png",
    "Q_I": "",
    "D_I": "tazawa.jpg"
  },
  "5": {
    "Q": "sentence5.png",
    "A": "1",
    "D": "desc5.png",
    "Q_I": "",
    "D_I": "shirakami_sanchi.jpg"
  },
  "6": {
    "Q": "sentence6.png",
    "A": "0",
    "D": "desc6.png",
    "Q_I": "sugicchi.png",
    "D_I": ""
  },
  "7": {
    "Q": "sentence7.png",
    "A": "1",
    "D": "desc7.png",
    "Q_I": "",
    "D_I": "popcorn.jpg"
  },
  "8": {
    "Q": "sentence8.png",
    "A": "1",
    "D": "desc8.png",
    "Q_I": "",
    "D_I": "toilet.jpg"
  },
  "9": {
    "Q": "sentence9.png",
    "A": "0",
    "D": "desc9.png",
    "Q_I": "",
    "D_I": ""
  },
  "10": {
    "Q": "sentence10.png",
    "A": "0",
    "D": "desc10.png",
    "Q_I": "",
    "D_I": "floor3.jpg"
  },
  "11": {
    "Q": "sentence11.png",
    "A": "1",
    "D": "desc11.png",
    "Q_I": "wedding_dress.jpg",
    "D_I": ""
  },
  "12": {
    "Q": "sentence12.png",
    "A": "1",
    "D": "desc12.png",
    "Q_I": "",
    "D_I": "school.jpg"
  },
  "13": {
    "Q": "sentence13.png",
    "A": "1",
    "D": "desc13.png",
    "Q_I": "",
    "D_I": "kanto.jpg"
  },
  "14": {
    "Q": "sentence14.png",
    "A": "1",
    "D": "desc14.png",
    "Q_I": "",
    "D_I": "kiritanpo.jpg"
  },
  "15": {
    "Q": "sentence15.png",
    "A": "1",
    "D": "desc15.png",
    "Q_I": "",
    "D_I": "shirakami_sanchi.jpg"
  },
  "16": {
    "Q": "sentence16.png",
    "A": "0",
    "D": "desc16.png",
    "Q_I": "",
    "D_I": "hatahata.png"
  },
  "17": {
    "Q": "sentence17.png",
    "A": "0",
    "D": "desc17.png",
    "Q_I": "",
    "D_I": "fireworks.jpg"
  },
  "18": {
    "Q": "sentence18.png",
    "A": "0",
    "D": "desc18.png",
    "Q_I": "",
    "D_I": "hatahata.png"
  },
  "19": {
    "Q": "sentence19.png",
    "A": "1",
    "D": "desc19.png",
    "Q_I": "",
    "D_I": "snow.jpg"
  },
  "20": {
    "Q": "sentence20.png",
    "A": "1",
    "D": "desc20.png",
    "Q_I": "",
    "D_I": "hand_spinner.jpg"
  },
}